slepc4py-stubs/__init__.pyi
slepc4py-stubs/__main__.pyi
slepc4py-stubs/py.typed
slepc4py-stubs/typing.pyi
slepc4py-stubs/SLEPc/BV.pyi
slepc4py-stubs/SLEPc/DS.pyi
slepc4py-stubs/SLEPc/EPS.pyi
slepc4py-stubs/SLEPc/FN.pyi
slepc4py-stubs/SLEPc/LME.pyi
slepc4py-stubs/SLEPc/MFN.pyi
slepc4py-stubs/SLEPc/NEP.pyi
slepc4py-stubs/SLEPc/PEP.pyi
slepc4py-stubs/SLEPc/RG.pyi
slepc4py-stubs/SLEPc/ST.pyi
slepc4py-stubs/SLEPc/SVD.pyi
slepc4py-stubs/SLEPc/Sys.pyi
slepc4py-stubs/SLEPc/Util.pyi
slepc4py-stubs/SLEPc/__init__.pyi
slepc4py-stubs/lib/__init__.pyi
slepc4py_stubs-0.1.1.dist-info/METADATA
slepc4py_stubs-0.1.1.dist-info/WHEEL
slepc4py_stubs-0.1.1.dist-info/licenses/LICENSE
slepc4py_stubs-0.1.1.dist-info/RECORD
